{
  "userGroup.done": "Hoàn thành",
  "userGroup.action": "Thao tác",
  "userGroup.editPermission": "Sửa nhóm quyền",
  "userGroup.groupFunction": "Cụm chức năng",
  "userGroup.functions": "Chức năng",
  "userGroup.tab": "Icon Sản phẩm / Tab",
  "userGroup.details": "Tài khoản trong nhóm quyền {name}",
  "userGroup.permission": "Quyền",
  "userGroup.permission.view": "Xem",
  "userGroup.permission.edit": "Sửa",
  "userGroup.permission.create": "Tạo",
  "userGroup.permission.approve": "Duyệt",
  "userGroup.permission.delete": "Xóa",
  "userGroup.code": "Mã nhóm quyền",
  "userGroup.code.required": "Mã nhóm quyền*",
  "userGroup.code.invalid": "Mã nhóm quyền không hợp lệ",
  "userGroup.description": "Mô tả nhóm quyền",
  "userGroup.description.required": "Mô tả nhóm quyền*",
  "userGroup.back": "Quay lại",
  "userGroup.save": "Lưu",
  "userGroup.processDone": "Xử lý thành công!",
  "userGroup.processFail": "Xử lý không thành công! Xin cảm ơn!",
  "userGroup.createDone": "Tạo mới thành công!",
  "userGroup.createFail": "Tạo mới thất bại!",
  "userGroup.deleteSuccess": "Xóa thành công!",
  "userGroup.deleteFail": "Xóa thất bại!",
  "userGroup.deleteGroup": "Xóa nhóm quyền",
  "userGroup.deleteGroup.confirmMessage": "Bạn có chắc muốn xóa nhóm quyền {name}",
  "userGroup.editGroup": "Sửa nhóm quyền",
  "userGroup.editGroup.confirmMessage": "Bạn có muốn sửa nhóm quyền {name}",
  "home.account": "TÀI KHOẢN",
  "home.buy.insurence": "MUA BẢO HIỂM",
  "home.contract": "QUẢN LÝ HỢP ĐỒNG",
  "home.rewward.point": "QUẢN LÝ ĐIỂM THƯỞNG",
  "home.rate": "QUẢN LÝ TỶ LỆ PHÍ",
  "home.cert.insurance": "GIẤY CHỨNG NHẬN BẢO HIỂM",
  "home.debt": "CÔNG NỢ",
  "home.statistical": "THỐNG KÊ",
  "home.status.contract": "THÔNG TIN",
  "home.unfinished": "Chưa hoàn thành:",
  "home.unpaid": "Chưa thanh toán:",
  "home.denied": "Bị từ chối:",
  "home.info.contractFinished": "Hợp đồng hoàn thành",
  "home.info.contractPending": "Hợp đồng chờ phê duyệt",
  "home.info.contractPendingBH": "Hợp đồng chờ phê duyệt",
  "home.info.contractExpire": "Hợp đồng sắp hết hạn",
  "home.info.contractApproved": "Hợp đồng đã duyệt",
  "home.info.contractRejected": "Hợp đồng bị từ chối",
  "home.info.accountApproved": "Tài khoản đã duyệt",
  "home.info.accountDebt": "Số tài khoản được cấp công nợ",
  "home.info.time": "Thời gian",
  "home.info.insuranceCompany": "Hãng bảo hiểm",
  "home.info.accountAwaitingApproval": "Tài khoản chờ phê duyệt",
  "home.info.debt": "Công nợ",
  "home.info.totalDebt": "Tổng công nợ",
  "home.info.revenue": "Doanh thu",
  "home.info.avatar": "Avatar",
  "home.info.contracts": "Số hợp đồng",
  "home.info.top10PartnerHighestRevenue": "Top 10 đối tác có doanh thu cao nhất",
  "home.info.top10PartnerLowestRevenue": "10 đối tác có doanh thu thấp nhất",
  "home.chart.title.CONTRACTS": "Số lượng HĐBH đã duyệt\n(Đvị: Hợp đồng)",
  "home.chart.title.REVENUE": "Doanh thu phí bảo hiểm\n(Đvị: Triệu đồng)",
  "home.chart.title.ACCOUNTS": "Số lượng tài khoản đã duyệt\n(Đvị: Tài khoản)",
  "home.chart.unit.CONTRACTS": "Hợp đồng",
  "home.chart.unit.REVENUE": "Triệu đồng",
  "home.chart.unit.ACCOUNTS": "Tài khoản",
  "home.chart.ALL": "Tổng",
  "home.chart.CC": "Ô tô",
  "home.chart.MC": "Xe máy",
  "home.chart.VTA": "Vững tâm an",
  "home.chart.HC": "Bảo hiểm Bảo an toàn gia",
  "home.chart.PHC": "Nhà tư nhân",
  "home.chart.selectInfo": "Chọn thông tin hiển thị",
  "home.chart.revenue.selectInfo": "Chọn loại doanh thu",
  "home.chart.bonus.selectInfo": "Chọn loại điểm thưởng",
  "home.chart.contract.selectInfo": "Chọn loại hợp đồng",
  "home.chart.debt.selectInfo": "Chọn loại công nợ",
  "home.chart.account.selectInfo": "Chọn loại tài khoản",
  "home.chart.revenue.ALL": "Tổng doanh thu",
  "home.chart.bonus.ALL": "Tổng điểm thưởng",
  "home.chart.debt.ALL": "Tổng công nợ",
  "home.chart.contract.ALL": "Tổng số hợp đồng",
  "home.chart.account.ALL": "Tất cả",
  "home.chart.revenue.CC": "Ô tô",
  "home.chart.revenue.MC": "Xe máy",
  "home.chart.revenue.VTA": "Vững tâm an",
  "home.chart.revenue.HC": "Bảo an toàn gia",
  "home.chart.revenue.HFC": "Nhà tư nhân",
  "home.chart.bonus.CC": "Ô tô",
  "home.chart.bonus.MC": "Xe máy",
  "home.chart.bonus.VTA": "Vững tâm an",
  "home.chart.bonus.HC": "Bảo an toàn gia",
  "home.chart.bonus.HFC": "Nhà tư nhân",
  "home.chart.debt.UNDUE": "Chưa đến hạn",
  "home.chart.debt.OUT_DATE": "Quá hạn",
  "home.chart.account.KHCN": "Khách hàng cá nhân",
  "home.chart.account.HT_IO": "Hỗ trợ kinh doanh",
  "home.chart.account.L1_30_DT": "Đối tác từ cấp 1 đến 30",
  "home.chart.account.LX_DT": "Đối tác vãng lai",
  "home.chart.account.HT_DT": "Hỗ trợ đối tác",
  "home.chart.account.DT_LK": "Đối tác trực thuộc cấp liền kề",
  "home.chart.account.DT_CD": "Đối tác cấp dưới",
  "home.chart.contract.CC": "Ô tô",
  "home.chart.contract.MC": "Xe máy",
  "home.chart.contract.VTA": "Vững tâm an",
  "home.chart.contract.HC": "Bảo an toàn gia",
  "home.chart.contract.HFC": "Nhà tư nhân",
  "home.chart.timeType.all": "7 ngày gần nhất",
  "home.chart.timeTypeRevenue.day": "Ngày",
  "home.chart.timeTypeRevenue.week": "Tuần",
  "home.chart.timeTypeRevenue.month": "Tháng",
  "home.chart.timeTypeRevenue.year": "Năm",
  "home.chart.timeType.current_week": "Tuần này",
  "home.chart.timeType.last_week": "Tuần trước",
  "home.chart.timeType.current_month": "Tháng này",
  "home.chart.timeType.last_month": "Tháng trước",
  "home.chart.timeType.current_year": "Năm nay",
  "home.chart.timeType.last_year": "Năm trước",
  "home.rating.point": "điểm",
  "home.rating.noData": "Không có dữ liệu",
  "home.insuranceCompany.ALL": "Tất cả",
  "AppName": "Tạo tài khoản",
  "title": "Thông tin đăng nhập",
  "account.title": "Thông tin đăng nhập",
  "account.backHome": "Trang chủ",
  "account.continue": "Tiếp tục",
  "account.continue.confirmMessage": "Bạn có muốn tiếp tục?",
  "account.done": "Hoàn thành",
  "account.done.confirmMessage": "Bạn có muốn hoàn thành?",
  "account.fullName": "Họ và tên*",
  "account.personalInfo": "Loại giấy tờ tùy thân*",
  "account.peopleID": "Chứng minh thư nhân dân",
  "account.citizenIdentify": "Căn cước công dân",
  "account.passpord": "Hộ chiếu",
  "account.born": "Ngày sinh",
  "account.identification": "Số giấy tờ tùy thân*",
  "account.gender": "Giới tính",
  "account.phoneNumber": "Số điện thoại*",
  "account.email": "Email*",
  "account.province": "Tỉnh/Thành phố*",
  "account.district": "Quận/Huyện*",
  "account.ward": "Phường/Xã*",
  "account.address": "Địa chỉ*",
  "account.permission": "Nhóm quyền*",
  "account.sale": "Kinh doanh",
  "account.supportSale": "Hỗ trợ kinh doanh",
  "account.bank": "Ngân hàng",
  "account.branch": "Chi Nhánh",
  "account.accountNumber": "Số tài khoản",
  "account.managerLevel": "Cấp quản lý",
  "account.managerLevelRequire": "Cấp quản lý*",
  "account.codeRefer": "Mã giới thiệu",
  "account.accountType": "Loại tài khoản",
  "account.accountCode": "Mã tài khoản",
  "account.status": "Trạng thái",
  "account.action": "Thao tác",
  "account.createdDate": "Ngày tạo đối tác",
  "account.status.lock": "Đã khóa",
  "account.status.acived": "Hoạt động",
  "account.status.waitapproved": "Chờ phê duyệt",
  "account.action.exist": "Đã có tài khoản",
  "account.action.notexist": "Chưa có tài khoản",
  "account.fullName.required": "Bạn phải nhập họ và tên",
  "account.fullName.inccorect": "Họ và tên không thể chứa ký tự đặc biệt",
  "account.icType.required": "Bạn phải chọn loại giấy tờ tùy thân",
  "account.identification.required": "Bạn phải nhập số giấy tờ tùy thân",
  "account.phoneNumber.required": "Bạn phải nhập số điện thoại",
  "account.email.required": "Bạn phải nhập email",
  "account.email.invalid": "Email sai định dạng",
  "account.province.required": "Bạn phải chọn tỉnh/thành phố",
  "account.district.required": "Bạn phải chọn quận/huyện",
  "account.ward.required": "Bạn phải chọn phường/xã",
  "account.address.required": "Bạn phải nhập địa chỉ",
  "account.permission.required": "Bạn phải chọn nhóm quyền",
  "account.bank.required": "Bạn phải chọn ngân hàng",
  "account.branch.required": "Bạn phải nhập chi nhánh",
  "account.accountNumber.required": "Bạn phải nhập số tài khoản",
  "account.managerLevel.required": "Bạn phải nhập mã cấp quản lý",
  "account.codeRefer.required": "Bạn phải nhập mã giới thiệu",
  "account.approveSuccessful": "Duyệt tài khoản  thành công ",
  "account.rejectSuccessful": "Từ chối tài khoản thành công",
  "account.accountApproval": "Duyệt tài khoản",
  "account.accountApproval.confirmMessage": "Bạn có muốn duyệt tài khoản {name}?",
  "account.refuseApproveAccount": "Từ chối duyệt tài khoản",
  "account.refuseApproveAccount.confirmMessage": "Bạn có muốn từ chối duyệt tài khoản {name}?",
  "account.createAccount": "Tạo tài khoản",
  "account.totalAccount": "Tổng số tài khoản",
  "account.exportReport": "Xuất báo cáo",
  "account.exportReportOption": "Bạn muốn xuất báo cáo những thông tin nào",
  "account.exportReportOption.icType": "CMND/CCCD/HC",
  "account.exportReportOption.fullName": "Họ và tên",
  "account.exportReportOption.dateOfBirth": "Ngày sinh",
  "account.exportReportOption.createdDate": "Ngày tạo",
  "account.exportReportOption.phoneNumber": "Số điện thoại",
  "account.exportReportOption.status": "Trạng thái",
  "account.exportReportOption.email": "Email",
  "account.exportReportOption.partnerLevel": "Cấp đối tác",
  "account.exportReportOption.address": "Địa chỉ",
  "account.exportReportOption.partnerCodeLevel1": "Mã đối tác cấp 1",
  "account.exportReportOption.managerCode": "Mã cấp quản lý",
  "account.createAccount.confirmMessage": "Bạn có muốn tạo tài khoản?",
  "account.editAccount": "Sửa tài khoản",
  "account.editAccount.confirmMessage": "Bạn có muốn sửa tài khoản {name}?",
  "account.updateSuccess": "Thay đổi thành công!",
  "account.updateSuccessNeedApproval": "Thông tin thay đổi đang chờ phê duyệt!",
  "account.createSuccess": "Tạo tài khoản thành công!",
  "account.createSuccessNeedApproval": "Tài khoản đang chờ phê duyệt!",
  "account.deleteAccount": "Xóa tài khoản",
  "account.deleteAccount.success": "Xóa tài khoản thành công!",
  "account.deleteAccount.confirmMessage": "Bạn có muốn xáo tài khoản {name}",
  "account.confirmOk": "Đồng ý",
  "account.confirmCancel": "Hủy",
  "account.back": "Quay lại",
  "account.back.confirmMessage": "Bạn có muốn quay lại?",
  "account.lockAccount": "Khóa tài khoản",
  "account.lockAccount.confirmMessage": "Bạn có muốn khóa tài khoản {name}?",
  "account.unlockAccount": "Mở khóa tài khoản",
  "account.unlockAccount.confirmMessage": "Bạn có muốn mở khóa tài khoản {name}?",
  "account.changeStatus.lock.success": "Khóa tài khoản thành công!",
  "account.changeStatus.lock.successNeedApproval": "Lệnh khóa đang chờ phê duyệt!",
  "account.changeStatus.active.success": "Mở khóa tài khoản thành công!",
  "account.changeStatus.active.successNeedApproval": "Lệnh mở khóa đang chờ phê duyệt!",
  "account.changeStatus.approve.success": "Phê duyệt tạo tài khoản thành công!",
  "account.changeStatus.reject.success": "Từ chối tạo tài khoản thành công!",
  "account.approvedBy": "Tài khoản duyệt",
  "account.changeDetail": "Các thay đổi gồm: {change}",
  "account.insurance.verhical": "BẢO HIỂM XE CƠ GIỚI",
  "account.insurance.car": "Bảo hiểm xe ô tô",
  "account.insurance.addOn": "Điều khoản bổ sung",
  "account.insurance.car.car01": "Bảo hiểm bắt buộc TNDS xe ô tô",
  "account.insurance.car.car01.info": "Là Bảo hiểm TNDS của chủ xe cơ giới đối với bên thứ 3 về thân thể, tính mạng và tài sản, thiệt hại về thân thể và tính mạng hành khách theo hợp đồng vận chuyển hành khách.",
  "account.insurance.car.car02": "Bảo hiểm TNDS tự nguyện xe ôtô",
  "account.insurance.car.car02.info": "Là Bảo hiểm chi trả cho phần trách nhiệm dân sự vượt mức trách nhiệm dân sự bắt buộc theo quy định của Nhà nước.",
  "account.insurance.car.car03": "Bảo hiểm vật chất xe ô tô",
  "account.insurance.car.car03.info": "Là Bảo hiểm bồi thường những thiệt hại vật chất xe xảy ra do: <br/> 1. Những tai nạn bất ngờ, ngoài sự kiểm soát của Chủ xe, Người được bảo hiểm trong những trường hợp: <br/>   - Đâm, va, lật, đổ, rơi, chìm; <br/>   - Hoả hoạn, cháy, nổ; <br/>  - Các vật thể khác rơi, va chạm vào. <br/> 2. Những tai họa bất khả kháng do thiên nhiên: Bão, gió lốc, lũ, lụt, triều cường, sụt/lở đất, sét đánh, động đất, mưa đá, sóng thần. <br/> 3. Mất toàn bộ xe do bị trộm, bị cướp. <br/> 4. Hành vi ác ý, cố tình phá hoại (loại trừ hành vi ác ý, cố tình phá hoại của Bên mua bảo hiểm, Chủ xe, Người được bảo hiểm, Người điều khiển xe và những người có quyền lợi liên quan đến sở hữu, khai thác và sử dụng Xe ô tô). <br/> 5. Ngoài ra, hãng Bảo hiểm còn bồi thường cho Bên mua bảo hiểm/Chủ xe những chi phí cần thiết và hợp lý theo thỏa thuận tại Hợp đồng bảo hiểm để thực hiện các công việc theo yêu cầu và chỉ dẫn của hãng Bảo hiểm khi xảy ra tổn thất (thuộc phạm vi bảo hiểm), bao gồm các chi phí:<br/>  - Chi phí ngăn ngừa hạn chế tổn thất phát sinh thêm; <br/>  - Chi phí cứu hộ và vận chuyển xe bị thiệt hại tới nơi sửa chữa gần nhất tối đa không vượt quá 10% số tiền bảo hiểm/vụ tổn thất. <br/> Trong mọi trường hợp, tổng số tiền bồi thường của hãng Bảo hiểm (bao gồm các chi phí trên) đối với một sự kiện bảo hiểm không vượt quá số tiền bảo hiểm (hay mức trách nhiệm bảo hiểm) ghi trên Giấy chứng nhận bảo hiểm/Hợp đồng bảo hiểm hoặc giá thị trường của Xe ô tô ngay trước khi xảy ra tổn thất tùy thuộc số tiền nào nhỏ hơn.",
  "account.insurance.car.car04": "Mức miễn thường có khấu trừ",
  "account.insurance.car.car04.info": "Mức miễn thường có khấu trừ",
  "account.insurance.car.car05": "Bảo hiểm lái, phụ xe và người ngồi trên xe",
  "account.insurance.car.car05.info": "Là Bảo hiểm thiệt hại thân thể đối với người được bảo hiểm do tai nạn khi đang ở trên xe, lên xuống xe trong quá trình xe",
  "account.insurance.car.car06": "Bảo hiểm TNDS của chủ xe với hàng hóa vận chuyển trên xe",
  "account.insurance.car.car06.info": "Là Bảo hiểm chi trả khi Chủ xe phải bồi thường cho chủ hàng về những tổn thất hàng hóa vận chuyển trên xe theo Bộ Luật dân sự trong những trường hợp xe bị đâm, va, lật, đổ, rơi, chìm; hỏa hoạn, cháy, nổ; bị các vật thể khác rơi, va chạm vào; những tai nạn bất khả kháng do thiên nhiên: bão, gió lốc, lũ, lụt, triều cường, sụt/lở đất, sét đánh, động đất, mưa đá, sóng thần; <br/> Ngoài ra,  còn thanh toán cho chủ xe các chi phí cần thiết và hợp lý: <br/> - Ngăn ngừa, giảm nhẹ tổn thất cho hàng hoá. <br/> - Bảo quản, xếp dỡ, lưu kho, lưu bãi hàng hoá trong quá trình vận chuyển do hậu quả của tai nạn. <br/> - Giám định tổn thất thuộc trách nhiệm bảo hiểm của Công ty Bảo hiểm. <br /> Trong mọi trường hợp, số tiền bồi thường  (bao gồm cả các chi phí trên) không vượt quá mức trách nhiệm ghi trên Giấy chứng nhận bảo hiểm.",
  "account.insurance.car.addSetting01": "Phí cơ bản tăng thêm",
  "account.insurance.car.addSetting01.info": "\n",
  "account.insurance.car.addSetting02": "Nợ bổ sung hồ sơ",
  "account.insurance.car.addSetting02.info": "\n",
  "account.insurance.car.BS01": "BS01 - Bảo hiểm thay thế mới",
  "account.insurance.car.BS01.info": "\n",
  "account.insurance.car.BS02": "BS02 - Bảo hiểm lựa chọn cơ sở sửa chữa",
  "account.insurance.car.BS02.info": "\n",
  "account.insurance.car.BS03": "BS03 - Bảo hiểm thuê xe trong thời gian sửa chữa",
  "account.insurance.car.BS03.info": "\n",
  "account.insurance.car.BS04": "BS04 - Bảo hiểm vật chất đối với xe miễn thuế, tạm nhập, tái xuất",
  "account.insurance.car.BS04.info": "\n",
  "account.insurance.car.BS05": "BS05 - Bảo hiểm vật chất xe cơ giới ngoài lãnh thổ Việt Nam",
  "account.insurance.car.BS05.info": "\n",
  "account.insurance.car.BS06": "BS06 - Bảo hiểm xe bị mất trộm, cướp bộ phận",
  "account.insurance.car.BS06.info": "\n",
  "account.insurance.car.BS07": "BS07 - Bảo hiểm vật chất xe cơ giới lưu hành tạm thời",
  "account.insurance.car.BS07.info": "\n",
  "account.insurance.car.BS08": "BS08 - Bảo hiểm vật chất xe cơ giới lưu hành tạm thời",
  "account.insurance.car.BS08.info": "\n",
  "account.insurance.car.BS09": "BS09 - Bảo hiểm xe chuyên dùng",
  "account.insurance.car.BS09.info": "\n",
  "account.insurance.car.BS10": "BS10 - Bảo hiểm xe tập lái",
  "account.insurance.car.BS10.info": "\n",
  "account.insurance.car.BS11": "BS11 - Bảo hiểm cho thiết bị lắp thêm",
  "account.insurance.car.BS11.info": "\n",
  "account.insurance.car.BS12": "BS12 - Bảo hiểm bồi thường theo giới hạn trách nhiệm",
  "account.insurance.car.BS12.info": "\n",
  "account.insurance.car.BS13": "BS13 - Bảo hiểm xe hoạt động trong khu vực nội bộ",
  "account.insurance.car.BS13.info": "\n",
  "account.insurance.car.BS14": "BS14 - Bảo hiểm gia hạn bảo hành xe ô tô",
  "account.insurance.car.BS14.info": "\n",
  "account.insurance.motobike": "Bảo hiểm xe máy",
  "account.insurance.motobike.motobike01": "Bảo hiểm bắt buộc TNDS của chủ xe mô tô- xe máy",
  "account.insurance.motobike.motobike01.info": "\n",
  "account.insurance.motobike.motobike02": "Bảo hiểm tai nạn người ngồi trên xe mô tô- xe máy",
  "account.insurance.motobike.motobike02.info": "\n",
  "account.insurance.people": "BẢO HIỂM CON NGƯỜI",
  "account.insurance.asset": "BẢO HIỂM TÀI SẢN KỸ THUẬT",
  "account.insurance.travel": "BẢO HIỂM DU LỊCH CHUYẾN ĐI",
  "account.insurance.life": "BẢO HIỂM NHÂN THỌ",
  "account.createFeeAndBonus": "Tạo phí và điểm thưởng",
  "account.createFeeAndBonus.feeRate": "Tỷ lệ phí",
  "account.createFeeAndBonus.bonusPoint": "Điểm thưởng",
  "users.excel.CAR_TNDS": "BHBB TNDS xe ô tô",
  "users.excel.CAR_TNDS_TN": "BH TNDSTN xe ôtô",
  "users.excel.CAR_VATCHAT": "BHVC xe ô tô",
  "users.excel.CAR_CONNGUOI": "BH lái, phụ xe và người ngồi trên xe",
  "users.excel.CAR_HANGHOA": "BH TNDS của chủ xe với hàng hóa vận chuyển trên xe",
  "users.excel.MOTOR_TNDS": "BH BB TNDS của chủ xe mô tô- xe máy",
  "users.excel.MOTOR_CONNGUOI": "BH tai nạn người ngồi trên xe mô tô- xe máy",
  "users.excel.VTA": "BH Vững Tâm An",
  "users.excel.ATG": "BH Bảo An Toàn Gia",
  "users.excel.PHC": "BH Nhà Tư Nhân",
  "partner.account.accountCode": "Mã tài khoản",
  "partner.account.accountCode.required": "Bạn phải nhập mã tài khoản",
  "partner.account.fullName": "Họ và tên",
  "partner.account.phoneNumber": "Số điện thoại",
  "partner.account.refByUser.invalid": "Mã giới thiệu không hợp lệ",
  "partner.account.valid": "Hợp lệ",
  "partner.account.inValid": "Không hợp lệ",
  "partner.account.status": "Trạng thái",
  "partner.account.status.DEACTIVATE": "Chờ phê duyệt",
  "partner.account.status.AWAITING_APPROVAL": "Chờ phê duyệt",
  "partner.account.status.LOCK": "Đã khóa",
  "partner.account.status.ACTIVE": "Hoạt động",
  "partner.account.status.REJECTED": "Bị từ chối",
  "partner.account.action": "Thao tác",
  "partner.account.email": "Email",
  "partner.account.referCode": "Mã giới thiệu",
  "partner.account.created": "Ngày tạo đối tác",
  "partner.account.searchInput": "Tìm kiếm tài khoản",
  "partner.account.group": "Nhóm đối tác",
  "partner.account.title": "Phê duyệt mở tài khoản",
  "partner.account.button.homePage": "Trang chủ",
  "partner.account.button.Continue": "Tiếp tục",
  "partner.account.changeDescription": "Mô tả thay đổi",
  "partner.account.level": "Cấp đối tác",
  "partner.account.managerId": "Mã cấp quản lý",
  "partner.account.close": "Đóng",
  "partner.account.waitingApproval": "Chờ phê duyệt",
  "partner.account.active": "Hoạt động",
  "partner.account.lock": "Đã khóa",
  "intro.step1.slogan": "Tiên phong trong lĩnh vực bảo hiểm số",
  "intro.step2.slogan": "Luôn đồng hành cùng khách hàng",
  "intro.step3.slogan": "Dễ dàng tăng thu nhập cùng InOn",
  "intro.step1.benefit1": "Toàn bộ sản phẩm được số hóa.",
  "intro.step1.benefit2": "Thanh toán online bằng nhiều hình thức.",
  "intro.step1.benefit3": "Nhận, Giấy chứng nhận bảo hiểm điện tử tức thì.",
  "intro.step2.benefit1": "Dễ dàng mua bảo hiểm mọi lúc mọi nơi.",
  "intro.step2.benefit2": "Minh bạch trong các điều khoản giao dịch.",
  "intro.step2.benefit3": "Bảo vệ quyền lợi của Khách hàng tối đa khi xảy ra tổn thất.",
  "intro.step3.benefit1": "Khai phá tiềm năng phát triển bản thân.",
  "intro.step3.benefit2": "Cơ hội tăng thu nhập không giới hạn.",
  "intro.step3.benefit3": "Xây dựng nền tảng vững chắc cho tương lai",
  "helpcenter.create.askedQuestion": "Câu hỏi thường gặp ",
  "helpcenter.create.userManual": "Hướng dẫn sử dụng",
  "helpcenter.create.document": "Tài liệu nghiệp vụ",
  "helpcenter.create.title": "Tạo mới",
  "helpcenter.create.draft": "Lưu nháp",
  "helpcenter.create.titleQuestion": "Tiêu đề câu hỏi (*)",
  "helpcenter.create.categories": "Danh mục câu hỏi (*)",
  "helpcenter.create.showPublic": "Hiển thị công khai",
  "helpcenter.create.info": "Thông tin",
  "helpcenter.create.permissionToView": "Phân quyền xem (*)",
  "helpcenter.create.answerContent": "Nội dung câu trả lời (*)",
  "helpcenter.create.salesPartner": "Đối tác bán hàng",
  "helpcenter.create.individualCustomers": "Khách hàng cá nhân",
  "helpcenter.create.questionFor": "Câu hỏi dành cho",
  "helpcenter.create.notRequiredSignin": "Không yêu cầu đăng nhập",
  "helpcenter.create.confirmCreate": "Bạn có muốn tạo mới câu hỏi này ?",
  "helpcenter.create.confirmSaveDraft": "Bạn có muốn lưu bản nháp này ?",
  "helpcenter.create.linkVideo": "Link video",
  "helpcenter.management.questionCode": "Mã câu hỏi",
  "helpcenter.management.title": "Tiêu đề",
  "helpcenter.management.category": "Danh mục",
  "helpcenter.management.status": "Tình trạng",
  "helpcenter.management.documentCode": "Mã tài liệu",
  "helpcenter.management.creator": "Người tạo",
  "helpcenter.management.releaseDate": "Ngày phát hành",
  "helpcenter.management.lastUpdateDate": "Ngày cập nhật cuối",
  "helpcenter.management.documentType": "Loại tài liệu",
  "helpcenter.management.documentLink": "Link tài liệu",
  "helpcenter.manangement.action.edit": "Chỉnh sửa",
  "helpcenter.manangement.action.view": "Xem chi tiết",
  "helpcenter.manangement.action.remove": "Xoá",
  "helpcenter.manangement.action.hidden": "Ẩn",
  "helpcenter.manangement.action.approval": "Phê duyệt",
  "helpcenter.manangement.action.reject": "Từ chối",
  "helpcenter.management.table.filter.all": "Tất cả",
  "helpcenter.create.error": "Có lỗi xảy ra , vui lòng thử lại !",
  "helpcenter.management.status.waitingApproval": "Chờ phê duyệt",
  "helpcenter.management.status.approvaled": "Đã phát hành",
  "helpcenter.management.status.rejected": "Bị từ chối",
  "helpcenter.management.status.disabled": "Ẩn",
  "helpcenter.management.status.draft": "Bản nháp",
  "helpcenter.create.category.success": "Tạo mới danh mục thành công !",
  "helpcenter.management.edit.confirm": "Bạn có chắc chắn muốn cập nhật câu hỏi này ?",
  "helpcenter.management.edit.title": "Cập nhật câu hỏi",
  "helpcenter.management.delete.confirm": "Bạn có muốn tiếp tục ?",
  "helpcenter.management.delete.title": "Bạn sắp xoá câu hỏi này vĩnh viễn. Bạn có muốn tiếp tục ?",
  "helpcenter.management.rejected.title": "Bạn muốn từ chối phê duyệt câu hỏi này ?",
  "helpcenter.management.rejected.reason": "Nhập lý do từ chối",
  "helpcenter.management.rejected.continue": "Tiếp tục",
  "helpcenter.management.rejected.back": "Quay lại",
  "helpcenter.management.approval.title": "Tài liệu sẽ được hiển thị công khai sau khi phê duyệt.",
  "helpcenter.management.disabled.title": "Người xem sẽ không nhìn thấy câu hỏi của bạn trên hệ thống. Bạn có muốn tiếp tục ?",
  "helpcenter.management.action.success": "Thao tác thành công !",
  "helpcenter.create.draft.success": "Lưu bản nháp thành công",
  "helpcenter.select.wellcome": "Xin chào, bạn muốn tìm: ",
  "helpcenter": "Trung tâm trợ giúp",
  "helpcenter.resultSearch.found": "Kết quả tìm kiếm",
  "helpcenter.resultSearch.notfound": "Xin lỗi, hiện tại không có kết quả tìm kiếm phù hợp. Vui lòng thử lại với từ khoá khác",
  "helpcenter.create.titleDocument": "Tiêu đề tài liệu (*)",
  "helpcenter.create.usermanualCategory": "Danh mục hướng dẫn (*)",
  "helpcenter.create.professionalCategory": "Danh mục tài liệu (*)",
  "helpcenter.edit.update.success": "Cập nhật thành công",
  "helpcente.management.totalQuestion": "Tổng số câu hỏi: ",
  "helpcente.management.totalDocument": "Tổng số tài liệu: ",
  "helpcente.management.showWith": "Hiển thị với ",
  "helpcenter.outPage": "Bạn chuẩn bị rời trang , dữ liệu đang nhập sẽ bị mất",
  "support.create.title": "Tạo mới yêu cầu",
  "support.sideNav.title": "Hỗ trợ 24/7",
  "support.wellCome": "Xin chào, Inon giúp gì được cho bạn?",
  "support.card.helpcenter": "Câu hỏi thường gặp, hướng dẫn sử dụng, tài liệu nghiệp vụ",
  "support.card.supportOnline": "Hỗ trợ trực tuyến",
  "support.card.createSupport": "Tạo yêu cầu hỗ trợ",
  "support.create.fullName": "Họ và tên (*)",
  "support.create.email": "Email (*)",
  "support.create.phoneNumber": "Số điện thoại (*)",
  "support.create.detailRequest": "Thông tin yêu cầu",
  "support.create.question.detailRequest": "Bạn đang cần hỗ trợ vấn đề gì? ",
  "support.create.radio.product": "Sản phẩm",
  "support.create.radio.product.detail": "Sản phẩm, dịch vụ, phí bảo hiểm",
  "support.create.radio.payment": "Thanh toán",
  "support.create.radio.payment.detail": "Thanh toán, hoá đơn",
  "support.create.radio.skill": "Kĩ thuật",
  "support.create.radio.skill.detail": "Xử lý sự cố hệ thống",
  "support.create.radio.insurance": "Bồi thường bảo hiểm",
  "support.create.radio.insurance.detail": "Thông báo tai nạn, yêu cầu bồi thường",
  "support.create.radio.serviceCustomer": "Dịch vụ khách hàng",
  "support.create.radio.serviceCustomer.detail": "Tài khoản, chức năng hệ thống",
  "support.create.radio.report": "Góp ý - phản hồi",
  "support.create.radio.report.detail": "Khiếu nại, phản ánh dịch vụ",
  "support.create.radio.other": "Khác",
  "support.create.titleProblem": "Tiêu đề yêu cầu (*)",
  "support.create.detail": "Mô tả chi tiết (*)",
  "suppot.create.fileSelected": "File đã chọn",
  "helpcenter.create.updateFile": "Tải lên tài liệu",
  "suppot.create.requestFinish": "Đã tạo mới yêu cầu hỗ trợ. Truy cập Quản lý yêu cầu để xem chi tiết.",
  "support.management.title": "Quản lý yêu cầu hỗ trợ",
  "support.management.requestCode": "Mã yêu cầu",
  "support.management.table.title": "Tiêu đề",
  "support.management.table.supporter": "Người xử lý",
  "support.management.table.status": "Trạng thái",
  "support.myrequest.title": "Yêu cầu cá nhân",
  "support.myrequest.table.requestCode": "Mã phiếu yêu cầu",
  "support.myrequest.table.title": "Tiêu đề",
  "support.myrequest.table.classify": "Phân loại",
  "support.create.channel": "Kênh",
  "support.create.forMe": "Dành cho tôi",
  "support.create.forGuest": "Dành cho khách",
  "support.create.priority": "Ưu tiên",
  "support.create.medium": "Trung bình",
  "support.create.high": "Cao",
  "support.management.myRequest": "Yêu cầu của tôi",
  "support.management.specifiedRequest": "Yêu cầu được chỉ định",
  "support.management.departmentRequestment": "Yêu cầu của bộ phận",
  "support.permission.title": "Phân quyền",
  "support.permission.management": "Quản lý",
  "support.permission.selectPermission": "Chọn phân quyền (*)",
  "support.permission.selectPermission.admin": "Điều phối",
  "support.permission.selectPermission.major": "Xử lý",
  "support.permission.table.screen": "Màn hình",
  "support.permission.table.detail": "Chi tiết",
  "support.permission.table.create": "Tạo mới yêu cầu",
  "support.permission.table.detailRequest": "Thông tin yêu cầu",
  "support.permission.table.advance": "Nâng cao (tạo yêu cầu khách, phân loại, ưu tiên)",
  "support.permission.table.managementRequest": "Quản lý yêu cầu",
  "support.permission.table.viewList": "Xem danh sách, lọc yêu cầu ",
  "support.permission.table.windowChat": "Cửa sổ chat",
  "support.permission.table.action": "Thao tác",
  "support.permission.table.myRequest": "Yêu cầu của tôi",
  "support.permission.table.nominated": "Được chỉ định",
  "support.permission.table.classified": "Nhóm phân loại",
  "support.permission.table.viewAll": "Xem tất cả",
  "support.permission.table.guest": "Khách",
  "support.permission.table.inon": "Nội bộ InOn",
  "support.permission.table.updateStatus": "Cập nhật trạng thái",
  "support.permission.table.point": "Chỉ định",
  "support.permission.table.addPeople": "Thêm người",
  "support.permission.table.prioritized": "Ưu tiên",
  "support.permission.uerGroup": "Nhóm quyền",
  "support.management.handlingStaff": "Nhân viên xử lý",
  "support.management.status.todo": "Chờ xử lý",
  "support.management.status.doing": "Đang xử lý",
  "support.management.status.done": "Hoàn tất",
  "support.detail.updateStatus": "Cập nhật trạng thái",
  "support.detail.infoCustommer": "Thông tin khách hàng",
  "support.detail.question.updateStatus": "Bạn có muốn cập nhật trạng thái đối với phiếu này ?",
  "support.detail.description": "Ghi chú",
  "support.detail.department": "Phòng ban",
  "support.detail.selectPrioritized": "Chọn mức độ ưu tiên",
  "support.detail.updateInfo": "Chỉnh sửa thông tin",
  "support.detail.type": "Phân loại xử lý",
  "support.detail.coordinator": "Quyền điều phối",
  "support.detail.handle": "Quyền xử lý",
  "support.management.operate": "Vận hành",
  "support.management.accountant": "Kế toán",
  "support.management.technology": "Kĩ thuật",
  "support.permission.edit.update": "Cập nhật phân quyền",
  "support.permission.edit.updatePermission": "Bạn có muốn lưu cập nhật phân quyền với người dùng này?",
  "support.permission.edit.deletePermission": "Xoá quyền",
  "support.permission.edit.deletePermission.content": "Người dùng này không thể xử lý các yêu cầu hỗ trợ, Bạn có muốn tiếp tục?",
  "support.detail.updateDetail": "Bạn có muốn thay đổi thông tin yêu cầu?",
  "support.create.popup.title": "Tạo yêu cầu thành công",
  "support.create.noPriority": "Không ưu tiên",
  "support.typeRequest": "Loại yêu cầu",
  "support.detail.voteScore": "Đánh giá",
  "support.detail.comment": "Nhận xét",
  "button.goback": "Quay lại",
  "filter.all": "Tất cả",
  "account.management.type": "Loại tài khoản"
}